{"vod_id": 2763050717, "stream_id": 0, "title": "pre-order this stream to watch it 3 minutes early plus gain access to purchasing an exclusive popcorn bucket \u3010Variety Grab Bag\u3011 Noay 3", "description": null, "created_at": "2026-05-03 08:03:31", "published_at": "2026-05-03 08:03:31", "thumbnail_url": "https://static-cdn.jtvnw.net/cf_vods/d3fi1amfgojobc/5d3b5e96a5b730acd365_noanoelle_317164880997_1777795406//thumb/thumb0-90x60.jpg", "duration": 11731, "chat_archived": true, "video_archived": false}