{"vod_id": 2738711002, "stream_id": 0, "title": "addressing the allegations (im innocent) before the SWAT team that's actually outside my house starts breaching \u3010Variety Grab Bag\u3011 Noapril 3", "description": null, "created_at": "2026-04-03 08:12:00", "published_at": "2026-04-03 08:12:00", "thumbnail_url": "https://static-cdn.jtvnw.net/cf_vods/d1m7jfoe9zdc1j/bfeda531da4b54678e66_noanoelle_318675519579_1775203915//thumb/thumb0-90x60.jpg", "duration": 10638, "chat_archived": true, "video_archived": false}