{"vod_id": 2687803380, "stream_id": 0, "title": "one last rodeo before i retire from the osha violation factory where i breach dams and also make the floor slippery \u3010INFRA Mods\u3011 Febnoary 3", "description": null, "created_at": "2026-02-03 08:03:54", "published_at": "2026-02-03 08:03:54", "thumbnail_url": "https://static-cdn.jtvnw.net/cf_vods/d1m7jfoe9zdc1j/24578a8b7633eb37f909_noanoelle_317508370266_1770105828//thumb/thumb2-90x60.jpg", "duration": 11419, "chat_archived": true, "video_archived": false}